[
    {
        "source":"Islamabad",
        "destination":"Islamabad",
        "seatNo":"",
        "transportNo":"R-1234",
        "transportMethod":"Rickshaw",
        "details":"get into it from F-11 market"
    },
    {
        "source":"Islamabad",
        "destination":"Skardu",
        "seatNo":"9E",
        "transportNo":"ISF-123",
        "transportMethod":"Flight",
        "details":"take flight from Islamabad Airport"
    },
    {
        "source":"Islamabad",
        "destination":"Skardu",
        "seatNo":"",
        "transportNo":"ISB-234",
        "transportMethod":"Bus",
        "details":""
    },
    {
        "source":"Skardu",
        "destination":"Multan",
        "seatNo":"",
        "transportNo":"SMB-234",
        "transportMethod":"Bus",
        "details":""
    },
    {
        "source":"Karachi",
        "destination":"Multan",
        "seatNo":"",
        "transportNo":"KMT-11",
        "transportMethod":"Train",
        "details":"AC coach compartment # 5"
    },
    {
        "source":"Multan",
        "destination":"Kashmir",
        "seatNo":"",
        "transportNo":"MKT-11",
        "transportMethod":"Train",
        "details":"platform 3 compartment 5"
    },
    {
        "source":"Kashmir",
        "destination":"Karachi",
        "seatNo":"",
        "transportNo":"KKB-13",
        "transportMethod":"Bus",
        "details":""
    },
    {
        "source":"Skardu",
        "destination":"Kashmir",
        "seatNo":"",
        "transportNo":"SKC-12",
        "transportMethod":"Coaster",
        "details":"arrive early"
    },
    {
        "source":"Kashmir",
        "destination":"Islamabad",
        "seatNo":"",
        "transportNo":"KIB-22",
        "transportMethod":"Bus",
        "details":""
    },
    {
        "source":"Lahore",
        "destination":"Islamabad",
        "seatNo":"",
        "transportNo":"LIB-23",
        "transportMethod":"Bus",
        "details":"from Niazi Express stop"
    },
    {
        "source":"Lahore",
        "destination":"Kashmir",
        "seatNo":"",
        "transportNo":"LKF-223",
        "transportMethod":"Flight",
        "details":""
    },
    {
        "source":"Kashmir",
        "destination":"Lahore",
        "seatNo":"",
        "transportNo":"KLF-332",
        "transportMethod":"Flight",
        "details":""
    }
]